breakable_list/__init__.py
breakable_list/_tool.py
breakable_list/_wrapper.py
interruptible_list/__init__.py
interruptible_list/_tool.py
interruptible_list/_wrapper.py
interruptible_list-0.2.dist-info/METADATA
interruptible_list-0.2.dist-info/WHEEL
interruptible_list-0.2.dist-info/top_level.txt
interruptible_list-0.2.dist-info/RECORD
