Metadata-Version: 2.1
Name: interruptible-list
Version: 0.2
Summary: Build a list from a iterable, interruptible by KeyboardInterrupt (SIGINT), and monitorable by SIGUSR1 and SIGUSR2.
Home-page: https://github.com/jb-leger/interruptible-list
Author: Jean-Benoist Leger
Author-email: jb@leger.tf
License: UNKNOWN
Platform: UNKNOWN
Classifier: Development Status :: 3 - Alpha
Classifier: License :: OSI Approved :: MIT License
Classifier: Programming Language :: Python :: 3 :: Only
Requires-Python: >=3.6
